satelite/__init__.py
satelite/config.py
satelite/sentinel2/__init__.py
satelite/sentinel2/fecth_unique_tile_date_pystac.py
satelite/sentinel2/fetch_unique_tile_date.py
satelite/sentinel2/get_tiles.py
satsure_core-0.0.2.dist-info/LICENCE.txt
satsure_core-0.0.2.dist-info/METADATA
satsure_core-0.0.2.dist-info/WHEEL
satsure_core-0.0.2.dist-info/top_level.txt
satsure_core-0.0.2.dist-info/RECORD
